.DS_Store
example_pkg/__init__.py
sparti/.DS_Store
sparti/__init__.py
sparti/BART/BART_M.py
sparti/BART/__init__.py
sparti/BART/p_class.py
sparti/BART/utility.py
sparti/BSPF/BSPF_M.py
sparti/BSPF/__init__.py
sparti/BSPF/bsp_p_class.py
sparti/BSPF/bsp_utility.py
sparti-0.0.12.dist-info/DESCRIPTION.rst
sparti-0.0.12.dist-info/METADATA
sparti-0.0.12.dist-info/RECORD
sparti-0.0.12.dist-info/WHEEL
sparti-0.0.12.dist-info/metadata.json
sparti-0.0.12.dist-info/top_level.txt
