Metadata-Version: 2.0
Name: sparti
Version: 0.0.12
Summary: Spatial partition inference
Home-page: https://github.com/xuhuifan/Sparti
Author: Xuhui Fan
Author-email: xhfan.ml@gmail.com
License: UNKNOWN
Platform: UNKNOWN
Classifier: Programming Language :: Python :: 3
Classifier: License :: OSI Approved :: MIT License
Classifier: Operating System :: OS Independent
Requires-Python: >=3.5
